cbzm/__init__.py
cbzm/cli.py
cbzm/signal.py
cbzm-1.0.0.dist-info/LICENSE
cbzm-1.0.0.dist-info/METADATA
cbzm-1.0.0.dist-info/WHEEL
cbzm-1.0.0.dist-info/entry_points.txt
cbzm-1.0.0.dist-info/top_level.txt
cbzm-1.0.0.dist-info/RECORD
