Metadata-Version: 2.1
Name: cbzm
Version: 1.0.0
Summary: cbz merge - merge comic archives
Author-email: Merilynn Bandy <hello@furudean.com>
Project-URL: Homepage, https://github.com/furudean/cbzm
Project-URL: Issues, https://github.com/furudean/cbzm/issues
Classifier: Programming Language :: Python :: 3
Classifier: License :: OSI Approved :: MIT License
Classifier: Operating System :: OS Independent
Requires-Python: >=3.11
License-File: LICENSE
Requires-Dist: colorama
Provides-Extra: dev
Requires-Dist: mypy ; extra == 'dev'
Requires-Dist: flake8 ; extra == 'dev'
Requires-Dist: black ; extra == 'dev'
Requires-Dist: types-setuptools ; extra == 'dev'
